[
  {
    "generator_name": "G1",
    "input_dim": 11,
    "output_dim": 2,
    "number_of_target_bidding_blocks": 2,
    "train_size": 7680,
    "test_size": 1920,
    "best_test_loss": 1.0100493916931252,
    "best_epoch": 496,
    "model_path": "models\\neural_network\\training\\trained_models\\G1_policy.pt",
    "metadata_path": "models\\neural_network\\training\\trained_models\\G1_policy_metadata.json",
    "history_path": "models\\neural_network\\training\\training_results\\G1_training_history.json"
  },
  {
    "generator_name": "G2",
    "input_dim": 11,
    "output_dim": 2,
    "number_of_target_bidding_blocks": 2,
    "train_size": 7680,
    "test_size": 1920,
    "best_test_loss": 1.5632648645199272e-07,
    "best_epoch": 162,
    "model_path": "models\\neural_network\\training\\trained_models\\G2_policy.pt",
    "metadata_path": "models\\neural_network\\training\\trained_models\\G2_policy_metadata.json",
    "history_path": "models\\neural_network\\training\\training_results\\G2_training_history.json"
  },
  {
    "generator_name": "W1",
    "input_dim": 11,
    "output_dim": 2,
    "number_of_target_bidding_blocks": 2,
    "train_size": 7680,
    "test_size": 1920,
    "best_test_loss": 1.9149416592275276e-06,
    "best_epoch": 126,
    "model_path": "models\\neural_network\\training\\trained_models\\W1_policy.pt",
    "metadata_path": "models\\neural_network\\training\\trained_models\\W1_policy_metadata.json",
    "history_path": "models\\neural_network\\training\\training_results\\W1_training_history.json"
  },
  {
    "generator_name": "W2",
    "input_dim": 11,
    "output_dim": 2,
    "number_of_target_bidding_blocks": 2,
    "train_size": 7680,
    "test_size": 1920,
    "best_test_loss": 3.9474863103805544e-05,
    "best_epoch": 139,
    "model_path": "models\\neural_network\\training\\trained_models\\W2_policy.pt",
    "metadata_path": "models\\neural_network\\training\\trained_models\\W2_policy_metadata.json",
    "history_path": "models\\neural_network\\training\\training_results\\W2_training_history.json"
  },
  {
    "generator_name": "W3",
    "input_dim": 11,
    "output_dim": 2,
    "number_of_target_bidding_blocks": 2,
    "train_size": 7680,
    "test_size": 1920,
    "best_test_loss": 1.6704125126202902,
    "best_epoch": 170,
    "model_path": "models\\neural_network\\training\\trained_models\\W3_policy.pt",
    "metadata_path": "models\\neural_network\\training\\trained_models\\W3_policy_metadata.json",
    "history_path": "models\\neural_network\\training\\training_results\\W3_training_history.json"
  }
]